LICENSE
README.md
setup.cfg
setup.py
PyWizardLite/__init__.py
PyWizardLite/pywizardlite.py
PyWizardLite.egg-info/PKG-INFO
PyWizardLite.egg-info/SOURCES.txt
PyWizardLite.egg-info/dependency_links.txt
PyWizardLite.egg-info/top_level.txt
PyWizardLite.egg-info/zip-safe