Metadata-Version: 2.1
Name: PyWizardLite
Version: 0.0.8
Summary: PyWizardLite automates downloading the correct Chrome driver and generates XPath expressions for visible elements using their text.
Home-page: https://github.com/4akhilkumar/PyWizardLite
Author: Sai Akhil Kumar Reddy N
Author-email: 4akhilkumar@gmail.com
License: Apache
Keywords: Python script,Selenium,ChromeDriver,XPath,Element visibility,Download,Web scraping,Automated testing
Classifier: Development Status :: 4 - Beta
Classifier: Intended Audience :: Developers
Classifier: License :: OSI Approved :: Apache Software License
Classifier: Programming Language :: Python :: 3
Classifier: Programming Language :: Python :: 3.7
Classifier: Programming Language :: Python :: 3.8
Classifier: Programming Language :: Python :: 3.9
Classifier: Programming Language :: Python :: 3.10
Classifier: Programming Language :: Python :: 3.11
License-File: LICENSE
